Metadata-Version: 2.3
Name: django-guid
Version: 3.5.2
Summary: Middleware that enables single request-response cycle tracing by injecting a unique ID into project logs
License: MIT
Keywords: asgi,async,async support,correlation,correlation-id,django,guid,log id,logging,logging id,middleware,request,request id,request-id,uuid,web,sentry,celery
Author: Jonas Krüger Svensson
Author-email: jonas-ks@hotmail.com
Maintainer: Sondre Lillebø Gundersen
Maintainer-email: sondrelg@live.no
Requires-Python: >=3.8,<4.0
Classifier: Development Status :: 5 - Production/Stable
Classifier: Environment :: Web Environment
Classifier: Framework :: Django
Classifier: Framework :: Django :: 4.2
Classifier: Framework :: Django :: 5.0
Classifier: Framework :: Django :: 5.1
Classifier: Intended Audience :: Developers
Classifier: License :: OSI Approved :: BSD License
Classifier: License :: OSI Approved :: MIT License
Classifier: Operating System :: OS Independent
Classifier: Programming Language :: Python
Classifier: Programming Language :: Python :: 3
Classifier: Programming Language :: Python :: 3.8
Classifier: Programming Language :: Python :: 3.9
Classifier: Programming Language :: Python :: 3.10
Classifier: Programming Language :: Python :: 3.11
Classifier: Programming Language :: Python :: 3.12
Classifier: Programming Language :: Python :: 3.13
Classifier: Topic :: Internet :: WWW/HTTP
Classifier: Topic :: Internet :: WWW/HTTP :: Dynamic Content
Classifier: Topic :: Internet :: WWW/HTTP :: WSGI
Classifier: Topic :: Software Development
Classifier: Topic :: Software Development :: Libraries
Classifier: Topic :: Software Development :: Libraries :: Application Frameworks
Classifier: Topic :: Software Development :: Libraries :: Python Modules
Requires-Dist: django (>=4.0,<5.0) ; python_version >= "3.8" and python_version < "3.10"
Requires-Dist: django (>=4.0,<6.0) ; python_version >= "3.10"
Requires-Dist: packaging
Project-URL: Documentation, https://django-guid.readthedocs.io/en/latest
Project-URL: Homepage, https://github.com/snok/django-guid
Project-URL: Repository, https://github.com/snok/django-guid
Project-URL: Release notes, https://github.com/snok/django-guid/releases
